thumbor_piliptc_engine/__init__.py
thumbor_piliptc_engine/engine.py
thumbor_piliptc_engine-7.4.7.4.dist-info/LICENSE
thumbor_piliptc_engine-7.4.7.4.dist-info/METADATA
thumbor_piliptc_engine-7.4.7.4.dist-info/WHEEL
thumbor_piliptc_engine-7.4.7.4.dist-info/top_level.txt
thumbor_piliptc_engine-7.4.7.4.dist-info/RECORD
