Metadata-Version: 2.1
Name: thumbor-piliptc-engine
Version: 7.4.7.4
Summary: Pil imaging engine for Thumbor with IPTC data passthrough
Home-page: https://github.com/gdegoulet/thumbor-piliptc-engine
Author: Guillaume Degoulet
Author-email: piliptc@degoulet.net
License: MIT
Keywords: thumbor imaging pillow iptc copyright tags
Classifier: Development Status :: 3 - Alpha
Classifier: Intended Audience :: Developers
Classifier: Intended Audience :: System Administrators
Classifier: License :: OSI Approved :: MIT License
Classifier: Natural Language :: English
Classifier: Operating System :: MacOS
Classifier: Operating System :: POSIX :: Linux
Classifier: Programming Language :: Python :: 3
Classifier: Programming Language :: Python :: 3.7
Classifier: Programming Language :: Python :: 3.8
Classifier: Programming Language :: Python :: 3.9
Classifier: Programming Language :: Python :: 3.10
Classifier: Programming Language :: Python :: 3.11
Classifier: Programming Language :: Python :: 3 :: Only
Classifier: Topic :: Internet :: WWW/HTTP :: Dynamic Content
Classifier: Topic :: Multimedia :: Graphics :: Presentation
Classifier: Environment :: Plugins
Requires-Python: >=3.7
License-File: LICENSE
Requires-Dist: thumbor (==7.4.7)
Requires-Dist: pillow (>=9.0)
Requires-Dist: JpegIPTC (>=1.4)
Provides-Extra: tests
Requires-Dist: black ; extra == 'tests'
Requires-Dist: colorama ; extra == 'tests'
Requires-Dist: flake8 ; extra == 'tests'
Requires-Dist: isort ; extra == 'tests'
Requires-Dist: pytest ; extra == 'tests'
Requires-Dist: pytest-cov ; extra == 'tests'
Requires-Dist: pytest-mock ; extra == 'tests'
Requires-Dist: twine ; extra == 'tests'
Requires-Dist: wheel ; extra == 'tests'
